datasette_vega/__init__.py
datasette_vega/static/main.3ff385c5.js
datasette_vega/static/main.3ff385c5.js.map
datasette_vega/static/main.429a6b0f.css
datasette_vega/static/main.429a6b0f.css.map
datasette_vega-0.6.1.dist-info/METADATA
datasette_vega-0.6.1.dist-info/RECORD
datasette_vega-0.6.1.dist-info/WHEEL
datasette_vega-0.6.1.dist-info/entry_points.txt
datasette_vega-0.6.1.dist-info/top_level.txt
