Metadata-Version: 2.1
Name: datasette-vega
Version: 0.6.1
Summary: A Datasette plugin that provides tools for generating charts using Vega
Home-page: https://github.com/simonw/datasette-vega
Author: Simon Willison
License: Apache License, Version 2.0
Platform: UNKNOWN
Requires-Dist: datasette
